Metadata-Version: 1.0
Name: ataiat-probability
Version: 0.1
Summary: Gaussian and Binomial distributions
Home-page: UNKNOWN
Author: Ashutosh A. Patwardhan
Author-email: ashutosh.patwardhan@iitbombay.org
License: UNKNOWN
Platform: UNKNOWN
